{"adult":false,"also_known_as":["Грэм Грин","Грэхем Грин"],"biography":"From Wikipedia, the free encyclopedia.\n\nGraham Greene (born June 22, 1952) is a Canadian actor who has worked on stage, and in film and TV productions in Canada, England and the United States.","birthday":"1952-06-22","deathday":"","homepage":"","id":6804,"imdb_id":"nm0001295","name":"Graham Greene","place_of_birth":"Six Nations Reserve - Ontario - Canada","popularity":1.632241,"profile_path":"/usYFo2sWDhL0QtCdTBnFwI353Eq.jpg"}