{"adult":false,"also_known_as":[],"biography":"​From Wikipedia, the free encyclopedia.  \n\nHenry Jackson Thomas, Jr. (born September 9, 1971) is an American actor and musician. He has appeared in more than 40 films and is best known for his role as Elliott in the 1982 Steven Spielberg film E.T. the Extra-Terrestrial.\n\nDescription above from the Wikipedia article Henry Thomas, licensed under CC-BY-SA, full list of contributors on Wikipedia.","birthday":"1971-09-09","deathday":"","homepage":"","id":9976,"imdb_id":"nm0001794","name":"Henry Thomas","place_of_birth":"San Antonio, Texas, USA","popularity":2.741347,"profile_path":"/iDUTadQ7R2GmOSQEH0grJQ9VTOh.jpg"}