{"adult":false,"also_known_as":[" William Fox "],"biography":"​From Wikipedia, the free encyclopedia.\n\nJames Fox OBE  (born William Fox, 19 May 1939) is an English actor.\n\nDescription above from the Wikipedia article James Fox, licensed under CC-BY-SA, full list of contributors on Wikipedia","birthday":"1939-05-19","deathday":"","homepage":"","id":1292,"imdb_id":"nm0289038","name":"James Fox","place_of_birth":"London, England, United Kingdom","popularity":1.076198,"profile_path":"/hhWJskOI5sM8gikgJTQJZidkGRb.jpg"}