{"adult":false,"also_known_as":[],"biography":"From Wikipedia, the free encyclopedia.\n\nFrank Oz (born Richard Frank Oznowicz; May 25, 1944) is a British-born American film director, actor, voice actor and puppeteer who is known for creating and performing the characters Miss Piggy and Fozzie Bear in The Muppet Show and for directing films, including the 1986 Little Shop Of Horrors remake and Dirty Rotten Scoundrels. He is also the operator and voice of Yoda in the Star Wars series.\n\nDescription above from the Wikipedia article Frank Oz, licensed under CC-BY-SA, full list of contributors on Wikipedia .","birthday":"1944-05-25","deathday":"","homepage":"","id":7908,"imdb_id":"nm0000568","name":"Frank Oz","place_of_birth":"Hereford, Herefordshire, England, United Kingdom ","popularity":2.909191,"profile_path":"/aLH5bYwMIlVxCe4rIDaEsVJqDKn.jpg"}